twisted_sshtools/__init__.py
twisted_sshtools/ssh.py
twisted_sshtools/starter.py
twisted_sshtools/test_credentials.py
twisted_sshtools/test_ssh.py
twisted_sshtools/test_starter.py
twisted_sshtools-2.2.6.dist-info/DESCRIPTION.rst
twisted_sshtools-2.2.6.dist-info/METADATA
twisted_sshtools-2.2.6.dist-info/RECORD
twisted_sshtools-2.2.6.dist-info/WHEEL
twisted_sshtools-2.2.6.dist-info/metadata.json
twisted_sshtools-2.2.6.dist-info/top_level.txt
