Metadata-Version: 2.0
Name: twisted-sshtools
Version: 2.2.6
Summary: Start processes via SSH with twisted.
Home-page: https://github.com/i4Ds/twisted-sshtools
Author: Ivo Nussbaumer
Author-email: ivo.nussbaumer@fhnw.ch
License: UNKNOWN
Platform: UNKNOWN
Requires-Dist: unittest2 (>=0.8.0)
Requires-Dist: pycrypto (>=2.6)
Requires-Dist: pyasn1 (>=0.1.7)
Requires-Dist: twisted (==16.6.0)
Requires-Dist: utwist (>=0.1.3)
Requires-Dist: twistit (>=0.2.1)
Requires-Dist: cryptography (>=1.2.2)
